{"name":"centos","postlist":[{"title":"CentOS7启动及排错","slug":"linux/CentOS7启动及排错","date":"2017-01-06T17:50:32.000Z","updated":"2018-04-22T08:27:28.687Z","comments":true,"path":"api/articles/linux/CentOS7启动及排错.json","excerpt":null,"keywords":null,"cover":null,"content":null,"raw":null,"categories":[{"name":"centos","path":"api/categories/centos.json"}],"tags":[{"name":"centos7","path":"api/tags/centos7.json"}]},{"title":"Systemd 入门教程：命令篇","slug":"linux/Systemd 入门教程：命令篇","date":"2017-05-06T01:31:25.000Z","updated":"2018-04-22T09:30:14.835Z","comments":true,"path":"api/articles/linux/Systemd 入门教程：命令篇.json","excerpt":null,"keywords":null,"cover":"http://zhangqifei.top/picture/ifeier/data/systemd.jpg","content":null,"raw":null,"categories":[{"name":"centos","path":"api/categories/centos.json"}],"tags":[{"name":"centos7","path":"api/tags/centos7.json"}]}]}